Workbook

Sheet Raw data
A1: Company | B1: Year | C1: Revenue | D1: Cost_of_Sales | E1: Gross_Profit | F1: Operating_Expenses | G1: Operating_Profit | H1: Finance_Costs | I1: Net_Profit | J1: Cash | K1: Inventory | L1: Current_Assets | M1: Current_Liabilities | N1: Total_Assets | O1: Total_Liabilities | P1: Shareholders_Equity | Q1: Short_Term_Debt | R1: Long_Term_Debt
A2: Alpha Foods Holdings Ltd | B2: 2022 | C2: 171890000 | D2: 130632000 | E2: 41258000 | F2: 20000000 | G2: 21258000 | H2: 2000000 | I2: 19258000 | J2: 12000000 | K2: 4000000 | L2: 25000000 | M2: 14500000 | N2: 55000000 | O2: 22000000 | P2: 33000000 | Q2: 5000000 | R2: 17000000 | Z2: =IF(ISNUMBER(B2), B2, 0) -> 2022
A3: Alpha Foods Holdings Ltd | B3: 2023 | C3: 180500000 | D3: 137000000 | E3: 43500000 | F3: 21000000 | G3: 22500000 | H3: 2100000 | I3: 20400000 | J3: 13000000 | K3: 4500000 | L3: 27000000 | M3: 15000000 | N3: 58000000 | O3: 23000000 | P3: 35000000 | Q3: 5200000 | R3: 17800000 | Z3: =IF(ISNUMBER(B3), B3, 0) -> 2023
A4: Alpha Foods Holdings Ltd | B4: 2024 | C4: 190000000 | D4: 145000000 | E4: 45000000 | F4: 22000000 | G4: 23000000 | H4: 2200000 | I4: 20800000 | J4: 13500000 | K4: 5000000 | L4: 28000000 | M4: 15500000 | N4: 60000000 | O4: 24000000 | P4: 36000000 | Q4: 5400000 | R4: 18600000 | Z4: =IF(ISNUMBER(B4), B4, 0) -> 2024
A5: Alpha Foods Holdings Ltd | B5: 2025 | C5: 200000000 | D5: 152000000 | E5: 48000000 | F5: 23000000 | G5: 25000000 | H5: 2300000 | I5: 22700000 | J5: 14500000 | K5: 5500000 | L5: 30000000 | M5: 16000000 | N5: 63000000 | O5: 25000000 | P5: 38000000 | Q5: 5600000 | R5: 19400000 | Z5: =IF(ISNUMBER(B5), B5, 0) -> 2025
A6: Beta Retail Group Ltd | B6: 2022 | C6: 112300000 | D6: 92000000 | E6: 20300000 | F6: 18000000 | G6: 2300000 | H6: 2500000 | I6: -200000 | J6: 5000000 | K6: 2000000 | L6: 10000000 | M6: 8300000 | N6: 30000000 | O6: 16000000 | P6: 14000000 | Q6: 6000000 | R6: 10000000 | Z6: =IF(ISNUMBER(B6), B6, 0) -> 2022
A7: Beta Retail Group Ltd | B7: 2023 | C7: 116000000 | D7: 95000000 | E7: 21000000 | F7: 18500000 | G7: 2500000 | H7: 2600000 | I7: -100000 | J7: 5200000 | K7: 2200000 | L7: 10500000 | M7: 8500000 | N7: 31000000 | O7: 16500000 | P7: 14500000 | Q7: 6200000 | R7: 10200000 | Z7: =IF(ISNUMBER(B7), B7, 0) -> 2023
A8: Beta Retail Group Ltd | B8: 2024 | C8: 120000000 | D8: 98000000 | E8: 22000000 | F8: 19000000 | G8: 3000000 | H8: 2700000 | I8: 300000 | J8: 5400000 | K8: 2400000 | L8: 11000000 | M8: 8800000 | N8: 32000000 | O8: 17000000 | P8: 15000000 | Q8: 6400000 | R8: 10400000 | Z8: =IF(ISNUMBER(B8), B8, 0) -> 2024
A9: Beta Retail Group Ltd | B9: 2025 | C9: 125000000 | D9: 102000000 | E9: 23000000 | F9: 19500000 | G9: 3500000 | H9: 2800000 | I9: 700000 | J9: 5600000 | K9: 2600000 | L9: 11500000 | M9: 9000000 | N9: 33000000 | O9: 17500000 | P9: 15500000 | Q9: 6600000 | R9: 10600000 | Z9: =IF(ISNUMBER(B9), B9, 0) -> 2025
A10: Gamma Consumer Stores Ltd | B10: 2022 | C10: 132500000 | D10: 103500000 | E10: 29000000 | F10: 17000000 | G10: 12000000 | H10: 1500000 | I10: 10500000 | J10: 7000000 | K10: 3000000 | L10: 12000000 | M10: 8000000 | N10: 40000000 | O10: 18000000 | P10: 22000000 | Q10: 4000000 | R10: 14000000 | Z10: =IF(ISNUMBER(B10), B10, 0) -> 2022
A11: Gamma Consumer Stores Ltd | B11: 2023 | C11: 138000000 | D11: 108000000 | E11: 30000000 | F11: 17500000 | G11: 12500000 | H11: 1600000 | I11: 10900000 | J11: 7500000 | K11: 3200000 | L11: 12500000 | M11: 8200000 | N11: 42000000 | O11: 18500000 | P11: 23500000 | Q11: 4200000 | R11: 14300000 | Z11: =IF(ISNUMBER(B11), B11, 0) -> 2023
A12: Gamma Consumer Stores Ltd | B12: 2024 | C12: 144000000 | D12: 112500000 | E12: 31500000 | F12: 18000000 | G12: 13500000 | H12: 1700000 | I12: 11800000 | J12: 7800000 | K12: 3400000 | L12: 13000000 | M12: 8500000 | N12: 44000000 | O12: 19000000 | P12: 25000000 | Q12: 4400000 | R12: 14600000 | Z12: =IF(ISNUMBER(B12), B12, 0) -> 2024
A13: Gamma Consumer Stores Ltd | B13: 2025 | C13: 150000000 | D13: 118000000 | E13: 32000000 | F13: 18500000 | G13: 13500000 | H13: 1800000 | I13: 11700000 | J13: 8000000 | K13: 3600000 | L13: 13500000 | M13: 8800000 | N13: 46000000 | O13: 19500000 | P13: 26500000 | Q13: 4600000 | R13: 14900000 | Z13: =IF(ISNUMBER(B13), B13, 0) -> 2025

Sheet Ratios
A1: Company | B1: Metric | C1: Gross Margin (%) | D1: Net Profit Margin (%) | E1: Operating Margin (%) | F1: Current Ratio | G1: Debt-to-Equity | H1: ROE (%) | I1: Inventory Turnover
A2: Alpha Foods Holdings Ltd | B2: 2022 | C2: ='Raw data'!E2/'Raw data'!D2 -> 0.31583379 | D2: ='Raw data'!I2/'Raw data'!C2 -> 0.11203677 | E2: ='Raw data'!G2/'Raw data'!C2 -> 0.12367212 | F2: ='Raw data'!L2/'Raw data'!M2 -> 1.7241379 | G2: ='Raw data'!N2/'Raw data'!P2 -> 1.6666667 | H2: ='Raw data'!I2/'Raw data'!P2 -> 0.58357576 | I2: ='Raw data'!D2/'Raw data'!K2 -> 32.658
A3: Alpha Foods Holdings Ltd | B3: 2023 | C3: ='Raw data'!E3/'Raw data'!D3 -> 0.31751825 | D3: ='Raw data'!I3/'Raw data'!C3 -> 0.11301939 | E3: ='Raw data'!G3/'Raw data'!C3 -> 0.12465374 | F3: ='Raw data'!L3/'Raw data'!M3 -> 1.8 | G3: ='Raw data'!N3/'Raw data'!P3 -> 1.6571429 | H3: ='Raw data'!I3/'Raw data'!P3 -> 0.58285714 | I3: ='Raw data'!D3/'Raw data'!K3 -> 30.444444
A4: Alpha Foods Holdings Ltd | B4: 2024 | C4: ='Raw data'!E4/'Raw data'!D4 -> 0.31034483 | D4: ='Raw data'!I4/'Raw data'!C4 -> 0.10947368 | E4: ='Raw data'!G4/'Raw data'!C4 -> 0.12105263 | F4: ='Raw data'!L4/'Raw data'!M4 -> 1.8064516 | G4: ='Raw data'!N4/'Raw data'!P4 -> 1.6666667 | H4: ='Raw data'!I4/'Raw data'!P4 -> 0.57777778 | I4: ='Raw data'!D4/'Raw data'!K4 -> 29
A5: Alpha Foods Holdings Ltd | B5: 2025 | C5: ='Raw data'!E5/'Raw data'!D5 -> 0.31578947 | D5: ='Raw data'!I5/'Raw data'!C5 -> 0.1135 | E5: ='Raw data'!G5/'Raw data'!C5 -> 0.125 | F5: ='Raw data'!L5/'Raw data'!M5 -> 1.875 | G5: ='Raw data'!N5/'Raw data'!P5 -> 1.6578947 | H5: ='Raw data'!I5/'Raw data'!P5 -> 0.59736842 | I5: ='Raw data'!D5/'Raw data'!K5 -> 27.636364
A6: Beta Retail Group Ltd | B6: 2022 | C6: ='Raw data'!E6/'Raw data'!D6 -> 0.22065217 | D6: ='Raw data'!I6/'Raw data'!C6 -> -0.0017809439 | E6: ='Raw data'!G6/'Raw data'!C6 -> 0.020480855 | F6: ='Raw data'!L6/'Raw data'!M6 -> 1.2048193 | G6: ='Raw data'!N6/'Raw data'!P6 -> 2.1428571 | H6: ='Raw data'!I6/'Raw data'!P6 -> -0.014285714 | I6: ='Raw data'!D6/'Raw data'!K6 -> 46
A7: Beta Retail Group Ltd | B7: 2023 | C7: ='Raw data'!E7/'Raw data'!D7 -> 0.22105263 | D7: ='Raw data'!I7/'Raw data'!C7 -> -0.00086206897 | E7: ='Raw data'!G7/'Raw data'!C7 -> 0.021551724 | F7: ='Raw data'!L7/'Raw data'!M7 -> 1.2352941 | G7: ='Raw data'!N7/'Raw data'!P7 -> 2.137931 | H7: ='Raw data'!I7/'Raw data'!P7 -> -0.0068965517 | I7: ='Raw data'!D7/'Raw data'!K7 -> 43.181818
A8: Beta Retail Group Ltd | B8: 2024 | C8: ='Raw data'!E8/'Raw data'!D8 -> 0.2244898 | D8: ='Raw data'!I8/'Raw data'!C8 -> 0.0025 | E8: ='Raw data'!G8/'Raw data'!C8 -> 0.025 | F8: ='Raw data'!L8/'Raw data'!M8 -> 1.25 | G8: ='Raw data'!N8/'Raw data'!P8 -> 2.1333333 | H8: ='Raw data'!I8/'Raw data'!P8 -> 0.02 | I8: ='Raw data'!D8/'Raw data'!K8 -> 40.833333
A9: Beta Retail Group Ltd | B9: 2025 | C9: ='Raw data'!E9/'Raw data'!D9 -> 0.2254902 | D9: ='Raw data'!I9/'Raw data'!C9 -> 0.0056 | E9: ='Raw data'!G9/'Raw data'!C9 -> 0.028 | F9: ='Raw data'!L9/'Raw data'!M9 -> 1.2777778 | G9: ='Raw data'!N9/'Raw data'!P9 -> 2.1290323 | H9: ='Raw data'!I9/'Raw data'!P9 -> 0.04516129 | I9: ='Raw data'!D9/'Raw data'!K9 -> 39.230769
A10: Gamma Consumer Stores Ltd | B10: 2022 | C10: ='Raw data'!E10/'Raw data'!D10 -> 0.28019324 | D10: ='Raw data'!I10/'Raw data'!C10 -> 0.079245283 | E10: ='Raw data'!G10/'Raw data'!C10 -> 0.090566038 | F10: ='Raw data'!L10/'Raw data'!M10 -> 1.5 | G10: ='Raw data'!N10/'Raw data'!P10 -> 1.8181818 | H10: ='Raw data'!I10/'Raw data'!P10 -> 0.47727273 | I10: ='Raw data'!D10/'Raw data'!K10 -> 34.5
A11: Gamma Consumer Stores Ltd | B11: 2023 | C11: ='Raw data'!E11/'Raw data'!D11 -> 0.27777778 | D11: ='Raw data'!I11/'Raw data'!C11 -> 0.078985507 | E11: ='Raw data'!G11/'Raw data'!C11 -> 0.09057971 | F11: ='Raw data'!L11/'Raw data'!M11 -> 1.5243902 | G11: ='Raw data'!N11/'Raw data'!P11 -> 1.787234 | H11: ='Raw data'!I11/'Raw data'!P11 -> 0.46382979 | I11: ='Raw data'!D11/'Raw data'!K11 -> 33.75
A12: Gamma Consumer Stores Ltd | B12: 2024 | C12: ='Raw data'!E12/'Raw data'!D12 -> 0.28 | D12: ='Raw data'!I12/'Raw data'!C12 -> 0.081944444 | E12: ='Raw data'!G12/'Raw data'!C12 -> 0.09375 | F12: ='Raw data'!L12/'Raw data'!M12 -> 1.5294118 | G12: ='Raw data'!N12/'Raw data'!P12 -> 1.76 | H12: ='Raw data'!I12/'Raw data'!P12 -> 0.472 | I12: ='Raw data'!D12/'Raw data'!K12 -> 33.088235
A13: Gamma Consumer Stores Ltd | B13: 2025 | C13: ='Raw data'!E13/'Raw data'!D13 -> 0.27118644 | D13: ='Raw data'!I13/'Raw data'!C13 -> 0.078 | E13: ='Raw data'!G13/'Raw data'!C13 -> 0.09 | F13: ='Raw data'!L13/'Raw data'!M13 -> 1.5340909 | G13: ='Raw data'!N13/'Raw data'!P13 -> 1.7358491 | H13: ='Raw data'!I13/'Raw data'!P13 -> 0.44150943 | I13: ='Raw data'!D13/'Raw data'!K13 -> 32.777778

Sheet Dashboards
B1: JSE FOOD RETAILERS -FINANCIAL ANALYSIS DASHBOARD
B2: Comparative performance Analysis (FY2022 - 2024)
B3: =TODAY() -> 46018
B5: A | C5: B | D5: C | E5: D | F5: E | G5: F
B6: Year | C6: Company | D6: Revenue | E6: Gross Margin % | F6: ROE % | G6: Debt-to-Equity | H6: Overall Risk Signal
B7: 2022 | C7: Alpha Foods Holdings Ltd | D7: =INDEX('Raw data'!C:C, MATCH(2022, 'Raw data'!B:B, 0)) -> 171890000 | E7: =IFERROR('Raw data'!E2/'Raw data'!C2,"") -> 0.2400256 | F7: =IFERROR('Raw data'!I2/'Raw data'!P2,"") -> 0.58357576 | G7: =IFERROR('Raw data'!O2/'Raw data'!P2,"") -> 0.66666667 | H7: =IF(OR(F7<=0, G7>1), "HIGH RISK", IF(OR(AND(F7>0, F7<0.15), AND(G7>=0.6, G7<=1)), "MODERATE", "HEALTHY")) -> MODERATE
B8: 2023 | C8: Alpha Foods Holdings Ltd | D8: =INDEX('Raw data'!C:C, MATCH(2023, 'Raw data'!B:B, 0)) -> 180500000 | E8: =IFERROR('Raw data'!E3/'Raw data'!C3,"") -> 0.24099723 | F8: =IFERROR('Raw data'!I3/'Raw data'!P3,"") -> 0.58285714 | G8: =IFERROR('Raw data'!O3/'Raw data'!P3,"") -> 0.65714286 | H8: =IF(OR(F8<=0, G8>1), "HIGH RISK", IF(OR(AND(F8>0, F8<0.15), AND(G8>=0.6, G8<=1)), "MODERATE", "HEALTHY")) -> MODERATE
B9: 2024 | C9: Alpha Foods Holdings Ltd | D9: =INDEX('Raw data'!C:C, MATCH(2024, 'Raw data'!B:B, 0)) -> 190000000 | E9: =IFERROR('Raw data'!E4/'Raw data'!C4,"") -> 0.23684211 | F9: =IFERROR('Raw data'!I4/'Raw data'!P4,"") -> 0.57777778 | G9: =IFERROR('Raw data'!O4/'Raw data'!P4,"") -> 0.66666667 | H9: =IF(OR(F9<=0, G9>1), "HIGH RISK", IF(OR(AND(F9>0, F9<0.15), AND(G9>=0.6, G9<=1)), "MODERATE", "HEALTHY")) -> MODERATE
B10: 2025 | C10: Alpha Foods Holdings Ltd | D10: =INDEX('Raw data'!C:C, MATCH(2025, 'Raw data'!B:B, 0)) -> 200000000 | E10: =IFERROR('Raw data'!E5/'Raw data'!C5,"") -> 0.24 | F10: =IFERROR('Raw data'!I5/'Raw data'!P5,"") -> 0.59736842 | G10: =IFERROR('Raw data'!O5/'Raw data'!P5,"") -> 0.65789474 | H10: =IF(OR(F10<=0, G10>1), "HIGH RISK", IF(OR(AND(F10>0, F10<0.15), AND(G10>=0.6, G10<=1)), "MODERATE", "HEALTHY")) -> MODERATE
B11: 2022 | C11: Beta Retail Group Ltd | D11: {=INDEX('Raw data'!C:C, MATCH(1, ('Raw data'!A:A="Beta Retail Group Ltd")*('Raw data'!B:B=2022), 0))} -> 112300000 | E11: =IFERROR('Raw data'!E6/'Raw data'!C6,"") -> 0.18076581 | F11: =IFERROR('Raw data'!I6/'Raw data'!P6,"") -> -0.014285714 | G11: =IFERROR('Raw data'!O6/'Raw data'!P6,"") -> 1.1428571 | H11: =IF(OR(F11<=0, G11>1), "HIGH RISK", IF(OR(AND(F11>0, F11<0.15), AND(G11>=0.6, G11<=1)), "MODERATE", "HEALTHY")) -> HIGH RISK
B12: 2023 | C12: Beta Retail Group Ltd | D12: {=INDEX('Raw data'!C:C, MATCH(1, ('Raw data'!A:A="Beta Retail Group Ltd")*('Raw data'!B:B=2023), 0))} -> 116000000 | E12: =IFERROR('Raw data'!E7/'Raw data'!C7,"") -> 0.18103448 | F12: =IFERROR('Raw data'!I7/'Raw data'!P7,"") -> -0.0068965517 | G12: =IFERROR('Raw data'!O7/'Raw data'!P7,"") -> 1.137931 | H12: =IF(OR(F12<=0, G12>1), "HIGH RISK", IF(OR(AND(F12>0, F12<0.15), AND(G12>=0.6, G12<=1)), "MODERATE", "HEALTHY")) -> HIGH RISK
B13: 2024 | C13: Beta Retail Group Ltd | D13: {=INDEX('Raw data'!C:C, MATCH(1, ('Raw data'!A:A="Beta Retail Group Ltd")*('Raw data'!B:B=2024), 0))} -> 120000000 | E13: =IFERROR('Raw data'!E8/'Raw data'!C8,"") -> 0.18333333 | F13: =IFERROR('Raw data'!I8/'Raw data'!P8,"") -> 0.02 | G13: =IFERROR('Raw data'!O8/'Raw data'!P8,"") -> 1.1333333 | H13: =IF(OR(F13<=0, G13>1), "HIGH RISK", IF(OR(AND(F13>0, F13<0.15), AND(G13>=0.6, G13<=1)), "MODERATE", "HEALTHY")) -> HIGH RISK
B14: 2025 | C14: Beta Retail Group Ltd | D14: =INDEX('Raw data'!C:C, MATCH(2025, 'Raw data'!B:B, 0)) -> 200000000 | E14: =IFERROR('Raw data'!E9/'Raw data'!C9,"") -> 0.184 | F14: =IFERROR('Raw data'!I9/'Raw data'!P9,"") -> 0.04516129 | G14: =IFERROR('Raw data'!O9/'Raw data'!P9,"") -> 1.1290323 | H14: =IF(OR(F14<=0, G14>1), "HIGH RISK", IF(OR(AND(F14>0, F14<0.15), AND(G14>=0.6, G14<=1)), "MODERATE", "HEALTHY")) -> HIGH RISK
B15: 2022 | C15: Gamma Consumer Stores Ltd | D15: {=INDEX('Raw data'!C:C, MATCH(1, ('Raw data'!A:A="Gamma Consumer Stores Ltd")*('Raw data'!B:B=2022), 0))} -> 132500000 | E15: =IFERROR('Raw data'!E10/'Raw data'!C10,"") -> 0.21886792 | F15: =IFERROR('Raw data'!I10/'Raw data'!P10,"") -> 0.47727273 | G15: =IFERROR('Raw data'!O10/'Raw data'!P10,"") -> 0.81818182 | H15: =IF(OR(F15<=0, G15>1), "HIGH RISK", IF(OR(AND(F15>0, F15<0.15), AND(G15>=0.6, G15<=1)), "MODERATE", "HEALTHY")) -> MODERATE
B16: 2023 | C16: Gamma Consumer Stores Ltd | D16: {=INDEX('Raw data'!C:C, MATCH(1, ('Raw data'!A:A="Gamma Consumer Stores Ltd")*('Raw data'!B:B=2023), 0))} -> 138000000 | E16: =IFERROR('Raw data'!E11/'Raw data'!C11,"") -> 0.2173913 | F16: =IFERROR('Raw data'!I11/'Raw data'!P11,"") -> 0.46382979 | G16: =IFERROR('Raw data'!O11/'Raw data'!P11,"") -> 0.78723404 | H16: =IF(OR(F16<=0, G16>1), "HIGH RISK", IF(OR(AND(F16>0, F16<0.15), AND(G16>=0.6, G16<=1)), "MODERATE", "HEALTHY")) -> MODERATE
B17: 2024 | C17: Gamma Consumer Stores Ltd | D17: {=INDEX('Raw data'!C:C, MATCH(1, ('Raw data'!A:A="Gamma Consumer Stores Ltd")*('Raw data'!B:B=2024), 0))} -> 144000000 | E17: =IFERROR('Raw data'!E12/'Raw data'!C12,"") -> 0.21875 | F17: =IFERROR('Raw data'!I12/'Raw data'!P12,"") -> 0.472 | G17: =IFERROR('Raw data'!O12/'Raw data'!P12,"") -> 0.76 | H17: =IF(OR(F17<=0, G17>1), "HIGH RISK", IF(OR(AND(F17>0, F17<0.15), AND(G17>=0.6, G17<=1)), "MODERATE", "HEALTHY")) -> MODERATE
B18: 2025 | C18: Gamma Consumer Stores Ltd | D18: =INDEX('Raw data'!C:C, MATCH(2025, 'Raw data'!B:B, 0)) -> 200000000 | E18: =IFERROR('Raw data'!E13/'Raw data'!C13,"") -> 0.21333333 | F18: =IFERROR('Raw data'!I13/'Raw data'!P13,"") -> 0.44150943 | G18: =IFERROR('Raw data'!O13/'Raw data'!P13,"") -> 0.73584906 | H18: =IF(OR(F18<=0, G18>1), "HIGH RISK", IF(OR(AND(F18>0, F18<0.15), AND(G18>=0.6, G18<=1)), "MODERATE", "HEALTHY")) -> MODERATE

Sheet Charts data
A1: Year | B1: Alpha Foods Holdings Ltd | C1: Beta Retail Group Ltd | D1: Gamma Consumer Stores Ltd
A2: 2022 | B2: 197000 | C2: 184000 | D2: 149000
A3: 2023 | B3: =197000*1.09 -> 214730 | C3: =C2*1.076 -> 197984 | D3: =D2*1.081 -> 161069
A4: 2024 | B4: =215000*1.11 -> 238650 | C4: =C3*1.071 -> 212040.86 | D4: =D3*1.075 -> 173149.17
A5: 2025 | B5: =238000*1.07 -> 254660 | C5: =C4*1.061 -> 224975.36 | D5: =D4*1.069 -> 185096.47

Sheet CAGR
A1: Year | B1: Alpha Foods Holdings Ltd | C1: Beta Retail Group Ltd | D1: Gamma Consumer Stores Ltd
A2: 2022 | B2: 197000 | C2: 184000 | D2: 149000
A3: 2023 | B3: =197000*1.09 -> 214730 | C3: =C2*1.076 -> 197984 | D3: =D2*1.081 -> 161069
A4: 2024 | B4: =215000*1.11 -> 238650 | C4: =C3*1.071 -> 212040.86 | D4: =D3*1.075 -> 173149.17
A5: 2025 | B5: =238000*1.07 -> 254660 | C5: =C4*1.061 -> 224975.36 | D5: =D4*1.069 -> 185096.47
A6: Highest Revenue CAGR | B6: =MAX((B5/B2)^(1/3)-1, (C5/C2)^(1/3)-1, (D5/D2)^(1/3)-1) -> 0.089343474 | C6: =(C5/C2)^(1/3)-1 -> 0.069315122 | D6: =(D5/D2)^(1/3)-1 -> 0.074988837
